spaceverseai/__init__.py
spaceverseai/api_wrapper.py
spaceverseai/example_usage.py
spaceverseai-1.0.0.dist-info/METADATA
spaceverseai-1.0.0.dist-info/WHEEL
spaceverseai-1.0.0.dist-info/entry_points.txt
spaceverseai-1.0.0.dist-info/top_level.txt
spaceverseai-1.0.0.dist-info/RECORD
