Metadata-Version: 2.4
Name: spaceverseai
Version: 1.0.0
Summary: Advanced Real-Time Voice Chat System with Emotion Detection and AI Integration
Author-email: SpaceVerse AI Team <support@spaceverse.ai>
Maintainer-email: SpaceVerse AI Team <support@spaceverse.ai>
License: MIT
Project-URL: Homepage, https://github.com/spaceverse-ai/spaceverse-ai
Project-URL: Bug Tracker, https://github.com/spaceverse-ai/spaceverse-ai/issues
Project-URL: Documentation, https://github.com/spaceverse-ai/spaceverse-ai/blob/main/API_Wrapper/API_WRAPPER_README.md
Project-URL: Source Code, https://github.com/spaceverse-ai/spaceverse-ai
Keywords: ai,voice-chat,emotion-detection,openai,websocket,real-time,speech,chatbot,machine-learning
Classifier: Development Status :: 5 - Production/Stable
Classifier: Intended Audience :: Developers
Classifier: License :: OSI Approved :: MIT License
Classifier: Operating System :: OS Independent
Classifier: Programming Language :: Python :: 3
Classifier: Programming Language :: Python :: 3.8
Classifier: Programming Language :: Python :: 3.9
Classifier: Programming Language :: Python :: 3.10
Classifier: Programming Language :: Python :: 3.11
Classifier: Programming Language :: Python :: 3.12
Classifier: Topic :: Software Development :: Libraries :: Python Modules
Classifier: Topic :: Communications :: Chat
Classifier: Topic :: Scientific/Engineering :: Artificial Intelligence
Classifier: Topic :: Multimedia :: Sound/Audio :: Speech
Requires-Python: >=3.8
Requires-Dist: aiohttp>=3.8.0
Requires-Dist: websockets>=11.0.0
Requires-Dist: typing-extensions>=4.0.0
Provides-Extra: dev
Requires-Dist: pytest>=7.0.0; extra == "dev"
Requires-Dist: pytest-asyncio>=0.21.0; extra == "dev"
Requires-Dist: black>=22.0.0; extra == "dev"
Requires-Dist: mypy>=1.0.0; extra == "dev"
Provides-Extra: extra
Requires-Dist: pillow>=9.0.0; extra == "extra"
Requires-Dist: numpy>=1.21.0; extra == "extra"
Provides-Extra: all
Requires-Dist: pytest>=7.0.0; extra == "all"
Requires-Dist: pytest-asyncio>=0.21.0; extra == "all"
Requires-Dist: black>=22.0.0; extra == "all"
Requires-Dist: mypy>=1.0.0; extra == "all"
Requires-Dist: pillow>=9.0.0; extra == "all"
Requires-Dist: numpy>=1.21.0; extra == "all"
